pyneed/__init__.py
pyneed/__main__.py
pyneed-0.0.1.dist-info/LICENSE
pyneed-0.0.1.dist-info/METADATA
pyneed-0.0.1.dist-info/WHEEL
pyneed-0.0.1.dist-info/top_level.txt
pyneed-0.0.1.dist-info/RECORD
